AUTHORS
AUTHORS.in
COPYING
MANIFEST.in
README.md
koan.spec
setup.py
bin/cobbler-register
bin/koan
koan/__init__.py
koan/app.py
koan/cexceptions.py
koan/configurator.py
koan/imagecreate.py
koan/openvzcreate.py
koan/qcreate.py
koan/register.py
koan/utils.py
koan/virtinstall.py
koan/vmwcreate.py
koan/xencreate.py
koan.egg-info/PKG-INFO
koan.egg-info/SOURCES.txt
koan.egg-info/dependency_links.txt
koan.egg-info/requires.txt
koan.egg-info/top_level.txt